PDB_score/PDBProcessor.py
PDB_score/ProteinStructure.py
PDB_score/__init__.py
PDB_score/alignment.py
PDB_score/core.py
PDB_score/main.py
PDB_score-1.1.2.dist-info/LICENSE
PDB_score-1.1.2.dist-info/METADATA
PDB_score-1.1.2.dist-info/WHEEL
PDB_score-1.1.2.dist-info/entry_points.txt
PDB_score-1.1.2.dist-info/top_level.txt
PDB_score-1.1.2.dist-info/RECORD
