Metadata-Version: 2.1
Name: PDB_score
Version: 1.1.2
Summary: A tool to massively calculate protein scores using PDB files.
Home-page: https://github.com/SiriNatsume/PDB-score
Author: SiriNatsume
Author-email: SiriNatsume@outlook.com
License: MIT
Keywords: protein,score,PDB,alignment,GDT
Classifier: Programming Language :: Python :: 3
Classifier: License :: OSI Approved :: MIT License
Classifier: Operating System :: OS Independent
Requires-Python: >=3.6
License-File: LICENSE
Requires-Dist: numpy
Requires-Dist: biopython
Requires-Dist: scipy
